{
  "collectionName": "components_mission_vision_values_page_our_values",
  "info": {
    "displayName": "Our Values"
  },
  "options": {},
  "attributes": {
    "title": {
      "type": "string",
      "required": true
    },
    "titleIcon": {
      "allowedTypes": [
        "images",
        "files",
        "videos",
        "audios"
      ],
      "type": "media",
      "multiple": false,
      "required": true
    },
    "ourValuesEntries": {
      "displayName": "Values Entries",
      "type": "component",
      "repeatable": true,
      "component": "mission-vision-values-page.values-entries",
      "required": true
    },
    "sectionImage": {
      "allowedTypes": [
        "images",
        "files",
        "videos",
        "audios"
      ],
      "type": "media",
      "multiple": false,
      "required": true
    }
  }
}
